yai18n/__init__.py
yai18n/main.py
yet_another_i18n-0.2.0.dist-info/METADATA
yet_another_i18n-0.2.0.dist-info/WHEEL
yet_another_i18n-0.2.0.dist-info/licenses/LICENSE.txt
yet_another_i18n-0.2.0.dist-info/RECORD
