Metadata-Version: 2.3
Name: yet-another-i18n
Version: 0.2.0
Summary: A lightweight and developer-friendly Python translation library designed for simplicity and flexibility.
Project-URL: Homepage, https://github.com/2mal3/yet-another-i18n
Project-URL: Repository, https://github.com/2mal3/yet-another-i18n
Project-URL: Issues, https://github.com/2mal3/yet-another-i18n/issues
Author-email: 2mal3 <56305732+2mal3@users.noreply.github.com>
License: MIT
Keywords: i18n,json,localization,translation
Classifier: Development Status :: 4 - Beta
Classifier: Intended Audience :: Developers
Classifier: License :: OSI Approved :: MIT License
Classifier: Operating System :: OS Independent
Classifier: Programming Language :: Python
Classifier: Programming Language :: Python :: 3
Classifier: Programming Language :: Python :: 3 :: Only
Classifier: Programming Language :: Python :: 3.8
Classifier: Programming Language :: Python :: 3.9
Classifier: Programming Language :: Python :: 3.10
Classifier: Programming Language :: Python :: 3.11
Classifier: Programming Language :: Python :: 3.12
Classifier: Programming Language :: Python :: 3.13
Classifier: Topic :: Software Development :: Internationalization
Classifier: Topic :: Software Development :: Libraries :: Python Modules
Classifier: Topic :: Software Development :: Localization
Classifier: Typing :: Typed
Requires-Python: >=3.8
